{
  "device": "openaps://indy-e1", 
  "pump": {
    "battery": {
      "status": "normal", 
      "voltage": 1.36
    }, 
    "status": {
      "status": "normal", 
      "timestamp": "2016-06-06T20:41:48.000Z", 
      "bolusing": false, 
      "suspended": false
    }, 
    "reservoir": 84.275, 
    "clock": "2016-06-06T13:41:16-07:00"
  }, 
  "openaps": {
    "suggested": {
      "bg": 147, 
      "temp": "absolute", 
      "snoozeBG": 105, 
      "timestamp": "2016-06-06T20:43:01.000Z", 
      "predBGs": {
        "COB": [
          147, 
          146, 
          145, 
          143, 
          142, 
          140, 
          138, 
          135, 
          133, 
          130, 
          127, 
          124, 
          121, 
          118, 
          115, 
          113, 
          111, 
          109, 
          108, 
          107, 
          106, 
          105, 
          105, 
          105, 
          105, 
          106, 
          107, 
          108, 
          109, 
          111, 
          113, 
          115, 
          118, 
          121, 
          124, 
          127, 
          130
        ], 
        "aCOB": [
          147, 
          151, 
          154, 
          157, 
          159, 
          161, 
          163, 
          164, 
          165, 
          165, 
          166, 
          165, 
          165, 
          164, 
          164, 
          164, 
          164, 
          164, 
          164, 
          165, 
          165, 
          166, 
          166, 
          167, 
          168, 
          169, 
          170, 
          172, 
          173, 
          175, 
          176, 
          178, 
          180, 
          182, 
          184, 
          185, 
          187
        ], 
        "IOB": [
          147, 
          146, 
          144, 
          141, 
          138, 
          134, 
          130, 
          125, 
          119, 
          113, 
          107, 
          100, 
          92, 
          85, 
          78, 
          71, 
          65, 
          59, 
          54, 
          49, 
          44, 
          39
        ]
      }, 
      "reason": "COB: 51, Dev: 31, BGI: -6.22, ISF: 74.1, Target: 111; 130-105 in range: no temp required, temp 0.55 ~ req 0.54U/hr", 
      "COB": 51, 
      "eventualBG": 130, 
      "tick": -1, 
      "IOB": 2.098
    }, 
    "iob": [
      {
        "netbasalinsulin": 1.15, 
        "activity": 0.0168, 
        "basaliob": 0.517, 
        "time": "2016-06-06T20:41:16.000Z", 
        "hightempinsulin": 1.5, 
        "bolussnooze": 0.737, 
        "iob": 2.098
      }, 
      {
        "netbasalinsulin": 1.15, 
        "activity": 0.017, 
        "basaliob": 0.505, 
        "time": "2016-06-06T20:46:16.000Z", 
        "hightempinsulin": 1.5, 
        "bolussnooze": 0.526, 
        "iob": 2.013
      }, 
      {
        "netbasalinsulin": 1.15, 
        "activity": 0.0174, 
        "basaliob": 0.492, 
        "time": "2016-06-06T20:51:16.000Z", 
        "hightempinsulin": 1.5, 
        "bolussnooze": 0.336, 
        "iob": 1.926
      }, 
      {
        "netbasalinsulin": 1.1, 
        "activity": 0.0177, 
        "basaliob": 0.478, 
        "time": "2016-06-06T20:56:16.000Z", 
        "hightempinsulin": 1.45, 
        "bolussnooze": 0.189, 
        "iob": 1.838
      }, 
      {
        "netbasalinsulin": 1.1, 
        "activity": 0.0181, 
        "basaliob": 0.464, 
        "time": "2016-06-06T21:01:16.000Z", 
        "hightempinsulin": 1.45, 
        "bolussnooze": 0.083, 
        "iob": 1.747
      }, 
      {
        "netbasalinsulin": 1.05, 
        "activity": 0.0186, 
        "basaliob": 0.448, 
        "time": "2016-06-06T21:06:16.000Z", 
        "hightempinsulin": 1.4, 
        "bolussnooze": 0.02, 
        "iob": 1.654
      }, 
      {
        "netbasalinsulin": 0.95, 
        "activity": 0.0191, 
        "basaliob": 0.431, 
        "time": "2016-06-06T21:11:16.000Z", 
        "hightempinsulin": 1.3, 
        "bolussnooze": 0, 
        "iob": 1.558
      }, 
      {
        "netbasalinsulin": 0.8, 
        "activity": 0.0197, 
        "basaliob": 0.412, 
        "time": "2016-06-06T21:16:16.000Z", 
        "hightempinsulin": 1.15, 
        "bolussnooze": 0, 
        "iob": 1.46
      }, 
      {
        "netbasalinsulin": 0.7, 
        "activity": 0.0199, 
        "basaliob": 0.391, 
        "time": "2016-06-06T21:21:16.000Z", 
        "hightempinsulin": 1.05, 
        "bolussnooze": 0, 
        "iob": 1.361
      }, 
      {
        "netbasalinsulin": 0.65, 
        "activity": 0.0201, 
        "basaliob": 0.369, 
        "time": "2016-06-06T21:26:16.000Z", 
        "hightempinsulin": 1, 
        "bolussnooze": 0, 
        "iob": 1.26
      }, 
      {
        "netbasalinsulin": 0.55, 
        "activity": 0.0203, 
        "basaliob": 0.344, 
        "time": "2016-06-06T21:31:16.000Z", 
        "hightempinsulin": 0.9, 
        "bolussnooze": 0, 
        "iob": 1.159
      }, 
      {
        "netbasalinsulin": 0.45, 
        "activity": 0.0204, 
        "basaliob": 0.319, 
        "time": "2016-06-06T21:36:16.000Z", 
        "hightempinsulin": 0.8, 
        "bolussnooze": 0, 
        "iob": 1.057
      }, 
      {
        "netbasalinsulin": 0.45, 
        "activity": 0.0203, 
        "basaliob": 0.293, 
        "time": "2016-06-06T21:41:16.000Z", 
        "hightempinsulin": 0.8, 
        "bolussnooze": 0, 
        "iob": 0.955
      }, 
      {
        "netbasalinsulin": 0.4, 
        "activity": 0.019, 
        "basaliob": 0.267, 
        "time": "2016-06-06T21:46:16.000Z", 
        "hightempinsulin": 0.75, 
        "bolussnooze": 0, 
        "iob": 0.86
      }, 
      {
        "netbasalinsulin": 0.35, 
        "activity": 0.0174, 
        "basaliob": 0.242, 
        "time": "2016-06-06T21:51:16.000Z", 
        "hightempinsulin": 0.7, 
        "bolussnooze": 0, 
        "iob": 0.773
      }, 
      {
        "netbasalinsulin": 0.3, 
        "activity": 0.0165, 
        "basaliob": 0.218, 
        "time": "2016-06-06T21:56:16.000Z", 
        "hightempinsulin": 0.65, 
        "bolussnooze": 0, 
        "iob": 0.691
      }, 
      {
        "netbasalinsulin": 0.3, 
        "activity": 0.0156, 
        "basaliob": 0.195, 
        "time": "2016-06-06T22:01:16.000Z", 
        "hightempinsulin": 0.65, 
        "bolussnooze": 0, 
        "iob": 0.612
      }, 
      {
        "netbasalinsulin": 0.35, 
        "activity": 0.0148, 
        "basaliob": 0.172, 
        "time": "2016-06-06T22:06:16.000Z", 
        "hightempinsulin": 0.65, 
        "bolussnooze": 0, 
        "iob": 0.539
      }, 
      {
        "netbasalinsulin": 0.4, 
        "activity": 0.0139, 
        "basaliob": 0.151, 
        "time": "2016-06-06T22:11:16.000Z", 
        "hightempinsulin": 0.65, 
        "bolussnooze": 0, 
        "iob": 0.469
      }, 
      {
        "netbasalinsulin": 0.45, 
        "activity": 0.013, 
        "basaliob": 0.131, 
        "time": "2016-06-06T22:16:16.000Z", 
        "hightempinsulin": 0.65, 
        "bolussnooze": 0, 
        "iob": 0.405
      }, 
      {
        "netbasalinsulin": 0.45, 
        "activity": 0.012, 
        "basaliob": 0.112, 
        "time": "2016-06-06T22:21:16.000Z", 
        "hightempinsulin": 0.65, 
        "bolussnooze": 0, 
        "iob": 0.344
      }, 
      {
        "netbasalinsulin": 0.5, 
        "activity": 0.0111, 
        "basaliob": 0.094, 
        "time": "2016-06-06T22:26:16.000Z", 
        "hightempinsulin": 0.65, 
        "bolussnooze": 0, 
        "iob": 0.289
      }, 
      {
        "netbasalinsulin": 0.55, 
        "activity": 0.0101, 
        "basaliob": 0.077, 
        "time": "2016-06-06T22:31:16.000Z", 
        "hightempinsulin": 0.65, 
        "bolussnooze": 0, 
        "iob": 0.238
      }, 
      {
        "netbasalinsulin": 0.55, 
        "activity": 0.0091, 
        "basaliob": 0.063, 
        "time": "2016-06-06T22:36:16.000Z", 
        "hightempinsulin": 0.65, 
        "bolussnooze": 0, 
        "iob": 0.193
      }, 
      {
        "netbasalinsulin": 0.6, 
        "activity": 0.0081, 
        "basaliob": 0.049, 
        "time": "2016-06-06T22:41:16.000Z", 
        "hightempinsulin": 0.65, 
        "bolussnooze": 0, 
        "iob": 0.152
      }, 
      {
        "netbasalinsulin": 0.65, 
        "activity": 0.0071, 
        "basaliob": 0.037, 
        "time": "2016-06-06T22:46:16.000Z", 
        "hightempinsulin": 0.65, 
        "bolussnooze": 0, 
        "iob": 0.116
      }, 
      {
        "netbasalinsulin": 0.65, 
        "activity": 0.0061, 
        "basaliob": 0.027, 
        "time": "2016-06-06T22:51:16.000Z", 
        "hightempinsulin": 0.65, 
        "bolussnooze": 0, 
        "iob": 0.086
      }, 
      {
        "netbasalinsulin": 0.65, 
        "activity": 0.0051, 
        "basaliob": 0.019, 
        "time": "2016-06-06T22:56:16.000Z", 
        "hightempinsulin": 0.65, 
        "bolussnooze": 0, 
        "iob": 0.061
      }, 
      {
        "netbasalinsulin": 0.6, 
        "activity": 0.004, 
        "basaliob": 0.012, 
        "time": "2016-06-06T23:01:16.000Z", 
        "hightempinsulin": 0.6, 
        "bolussnooze": 0, 
        "iob": 0.04
      }, 
      {
        "netbasalinsulin": 0.6, 
        "activity": 0.0032, 
        "basaliob": 0.007, 
        "time": "2016-06-06T23:06:16.000Z", 
        "hightempinsulin": 0.6, 
        "bolussnooze": 0, 
        "iob": 0.024
      }, 
      {
        "netbasalinsulin": 0.55, 
        "activity": 0.0024, 
        "basaliob": 0.004, 
        "time": "2016-06-06T23:11:16.000Z", 
        "hightempinsulin": 0.55, 
        "bolussnooze": 0, 
        "iob": 0.013
      }, 
      {
        "netbasalinsulin": 0.45, 
        "activity": 0.0016, 
        "basaliob": 0.002, 
        "time": "2016-06-06T23:16:16.000Z", 
        "hightempinsulin": 0.45, 
        "bolussnooze": 0, 
        "iob": 0.005
      }, 
      {
        "netbasalinsulin": 0.35, 
        "activity": 0.0008, 
        "basaliob": 0, 
        "time": "2016-06-06T23:21:16.000Z", 
        "hightempinsulin": 0.35, 
        "bolussnooze": 0, 
        "iob": 0.001
      }, 
      {
        "netbasalinsulin": 0.2, 
        "activity": 0.0001, 
        "basaliob": 0, 
        "time": "2016-06-06T23:26:16.000Z", 
        "hightempinsulin": 0.2, 
        "bolussnooze": 0, 
        "iob": 0
      }, 
      {
        "netbasalinsulin": 0.1, 
        "activity": 0, 
        "basaliob": 0, 
        "time": "2016-06-06T23:31:16.000Z", 
        "hightempinsulin": 0.1, 
        "bolussnooze": 0, 
        "iob": 0
      }, 
      {
        "netbasalinsulin": 0, 
        "activity": 0, 
        "basaliob": 0, 
        "time": "2016-06-06T23:36:16.000Z", 
        "hightempinsulin": 0, 
        "bolussnooze": 0, 
        "iob": 0
      }
    ], 
    "enacted": {
      "bg": 150, 
      "temp": "absolute", 
      "snoozeBG": 146, 
      "recieved": true, 
      "predBGs": {
        "COB": [
          150, 
          151, 
          152, 
          152, 
          152, 
          152, 
          152, 
          151, 
          149, 
          147, 
          145, 
          143, 
          140, 
          136, 
          133, 
          129, 
          125, 
          121, 
          118, 
          115, 
          112, 
          109, 
          107, 
          105, 
          103, 
          102, 
          101, 
          100, 
          100, 
          100, 
          101, 
          102, 
          103, 
          104, 
          106, 
          108, 
          111
        ], 
        "aCOB": [
          150, 
          154, 
          157, 
          160, 
          163, 
          165, 
          167, 
          168, 
          169, 
          169, 
          169, 
          168, 
          166, 
          164, 
          162, 
          159, 
          157, 
          154, 
          152, 
          149, 
          147, 
          145, 
          143, 
          141, 
          140, 
          138, 
          137, 
          136, 
          136, 
          135, 
          135, 
          136, 
          136, 
          137, 
          137, 
          138, 
          139
        ], 
        "IOB": [
          150, 
          150, 
          150, 
          149, 
          147, 
          145, 
          142, 
          137, 
          132, 
          126, 
          119, 
          112, 
          103, 
          94, 
          85, 
          76, 
          67, 
          58, 
          50, 
          42, 
          39
        ]
      }, 
      "reason": "COB: 52, Dev: 42, BGI: -6.04, ISF: 74.1, Target: 111; Eventual BG 111>=111, 27m@1.460 = 0.657 > req 0+0.1U", 
      "rate": 0.55, 
      "COB": 52, 
      "eventualBG": 111, 
      "timestamp": "2016-06-06T20:33:26.000Z", 
      "duration": 30, 
      "tick": "+1", 
      "IOB": 2.183
    }
  }, 
  "mmtune": {
    "scanDetails": [
      [
        "916.564", 
        5, 
        -68
      ], 
      [
        "916.588", 
        5, 
        -59
      ], 
      [
        "916.612", 
        4, 
        -67
      ], 
      [
        "916.636", 
        4, 
        -67
      ], 
      [
        "916.660", 
        5, 
        -58
      ], 
      [
        "916.684", 
        5, 
        -58
      ], 
      [
        "916.708", 
        5, 
        -66
      ]
    ], 
    "setFreq": 916.684, 
    "timestamp": "2016-06-06T20:41:27.000Z", 
    "usedDefault": false
  }
}